[
  {
    "code": "PRES",
    "condition": null,
    "impact": "en cours",
    "law": "Elaboration : art. L. 153-11 du CU\nRevision : art. L. 153-32 du CU",
    "name": "Délibération de prescription du conseil municipal ou communautaire",
    "name_sudocuh": "Prescription",
    "order": 1,
    "phases": "Définition des modalités",
    "scope_liste": [
      "pp",
      "ppi",
      "rms",
      "m",
      "ms",
      "mlh"
    ],
    "scope_sugg": [
      "pp",
      "ppi",
      "rms"
    ],
    "structurant": true
  },
  {
    "code": null,
    "condition": null,
    "impact": "en cours",
    "law": null,
    "name": "Délibération de prescription du conseil métropolitain",
    "name_sudocuh": null,
    "order": 2,
    "phases": null,
    "scope_liste": [
      "ppi"
    ],
    "scope_sugg": [],
    "structurant": true
  },
  {
    "code": "ARRLANC",
    "condition": null,
    "impact": null,
    "law": null,
    "name": "Arrêté de lancement de la procédure",
    "name_sudocuh": null,
    "order": 3,
    "phases": "Définition des modalités",
    "scope_liste": [
      "m",
      "ms",
      "mlh"
    ],
    "scope_sugg": [
      "m",
      "ms",
      "mlh"
    ],
    "structurant": true
  },
  {
    "code": null,
    "condition": null,
    "impact": null,
    "law": null,
    "name": "Exemption automatique d'évaluation environnementale",
    "name_sudocuh": null,
    "order": 4,
    "phases": null,
    "scope_liste": [
      "mlh"
    ],
    "scope_sugg": [],
    "structurant": true
  },
  {
    "code": "NOTPROJ",
    "condition": null,
    "impact": null,
    "law": null,
    "name": "Notification du projet ou demande de DUP",
    "name_sudocuh": null,
    "order": 5,
    "phases": null,
    "scope_liste": [
      "mc"
    ],
    "scope_sugg": [
      "mc"
    ],
    "structurant": true
  },
  {
    "code": "DELIBDISPOPUB",
    "condition": null,
    "impact": null,
    "law": null,
    "name": "Délibération modalités de mise à disposition du public",
    "name_sudocuh": null,
    "order": 6,
    "phases": null,
    "scope_liste": [
      "ms"
    ],
    "scope_sugg": [
      "ms"
    ],
    "structurant": false
  },
  {
    "code": "NOTMOD",
    "condition": null,
    "impact": null,
    "law": null,
    "name": "Notification de la procédure aux PPA",
    "name_sudocuh": null,
    "order": 7,
    "phases": null,
    "scope_liste": [
      "pp",
      "ppi",
      "rms",
      "m",
      "ms",
      "mc"
    ],
    "scope_sugg": [
      "pp",
      "ppi",
      "rms",
      "m",
      "ms",
      "mc"
    ],
    "structurant": true
  },
  {
    "code": null,
    "condition": null,
    "impact": null,
    "law": null,
    "name": "Transmission du courrier d'association et de la lettre d'information régionale",
    "name_sudocuh": null,
    "order": 8,
    "phases": null,
    "scope_liste": [
      "pp",
      "ppi"
    ],
    "scope_sugg": [],
    "structurant": false
  },
  {
    "code": "DELIBOPENZ",
    "condition": "Délibération qui justifie l'utilité de cette ouverture au regard des capacités d'urbanisation encore inexploitées dans les zones déjà urbanisées et la faisabilité opérationnelle d'un projet dans ces zones.\nObligatoire SI le projet de modification porte sur l'ouverture à l'urbanisation d'une zone",
    "impact": null,
    "law": null,
    "name": "Délibération qui justifie l'utilité de l'ouverture à l'urbanisation d'une zone",
    "name_sudocuh": null,
    "order": 9,
    "phases": null,
    "scope_liste": [
      "m"
    ],
    "scope_sugg": [],
    "structurant": false
  },
  {
    "code": "DELOMC",
    "condition": "Obligatoire pour pp, ppi et rms, facultatif pour les autres sauf si évaluation environnementale",
    "impact": null,
    "law": "Elaboration : art. L. 153-11 du CU Revision : art. L. 153-32 du CU  et dans les 2 cas : articles L. 103-2, L. 103-3 et L. 103-4 du code de l’urbanisme",
    "name": "Délibération ou arrêté définissant les objectifs et modalités concertation",
    "name_sudocuh": "Délibération ou arrêté définissant les objectifs et modalités concertation",
    "order": 10,
    "phases": "Définition des modalités",
    "scope_liste": [
      "pp",
      "ppi",
      "rms",
      "m",
      "ms",
      "mc",
      "mlh"
    ],
    "scope_sugg": [],
    "structurant": false
  },
  {
    "code": "DELMODCOM",
    "condition": null,
    "impact": null,
    "law": "art. L. 153-8 (1°) du code de l'urbanisme",
    "name": "Délibération modalités de collaboration avec les communes",
    "name_sudocuh": "Délibération modalités de collaboration avec les communes",
    "order": 11,
    "phases": "Définition des modalités",
    "scope_liste": [
      "ppi"
    ],
    "scope_sugg": [],
    "structurant": false
  },
  {
    "code": "RECRUITBE",
    "condition": null,
    "impact": null,
    "law": null,
    "name": "Recrutement d'un bureau d'études",
    "name_sudocuh": null,
    "order": 12,
    "phases": "Définition des modalités",
    "scope_liste": [
      "pp",
      "ppi",
      "rms",
      "m",
      "ms",
      "mlh"
    ],
    "scope_sugg": [
      "pp",
      "ppi",
      "rms",
      "m",
      "ms"
    ],
    "structurant": false
  },
  {
    "code": "RECRUITAMO",
    "condition": null,
    "impact": null,
    "law": null,
    "name": "Recrutement d'un AMO",
    "name_sudocuh": null,
    "order": 13,
    "phases": null,
    "scope_liste": [
      "pp",
      "ppi"
    ],
    "scope_sugg": [
      "pp",
      "ppi"
    ],
    "structurant": false
  },
  {
    "code": "REUPPA",
    "condition": null,
    "impact": null,
    "law": null,
    "name": "Réunion des PPA",
    "name_sudocuh": "Réunion des PPA",
    "order": 14,
    "phases": "Toutes phases",
    "scope_liste": [
      "pp",
      "ppi",
      "rms",
      "m",
      "ms",
      "mc",
      "mlh"
    ],
    "scope_sugg": [],
    "structurant": false
  },
  {
    "code": "REUGP",
    "condition": null,
    "impact": null,
    "law": null,
    "name": "Réunion de concertation grand public",
    "name_sudocuh": null,
    "order": 15,
    "phases": "Toutes phases",
    "scope_liste": [
      "pp",
      "ppi",
      "rms",
      "m",
      "ms",
      "mc",
      "mlh"
    ],
    "scope_sugg": [],
    "structurant": false
  },
  {
    "code": "CONSDIAG",
    "condition": null,
    "impact": null,
    "law": null,
    "name": "Phase de construction du diagnostic",
    "name_sudocuh": null,
    "order": 16,
    "phases": null,
    "scope_liste": [
      "pp",
      "ppi",
      "rms",
      "m",
      "ms",
      "mlh"
    ],
    "scope_sugg": [
      "pp",
      "ppi"
    ],
    "structurant": false
  },
  {
    "code": "PAC",
    "condition": null,
    "impact": null,
    "law": null,
    "name": "Transmission du porter-à-connaissance",
    "name_sudocuh": null,
    "order": 17,
    "phases": null,
    "scope_liste": [
      "pp",
      "ppi"
    ],
    "scope_sugg": [],
    "structurant": true
  },
  {
    "code": "CHECKPAC",
    "condition": null,
    "impact": null,
    "law": "L. 132-2 du CU",
    "name": "Prise en compte du porter à connaissance dans le projet",
    "name_sudocuh": null,
    "order": 18,
    "phases": "Diagnostic",
    "scope_liste": [
      "pp",
      "ppi"
    ],
    "scope_sugg": [
      "pp",
      "ppi"
    ],
    "structurant": false
  },
  {
    "code": "ASKNOTE",
    "condition": null,
    "impact": null,
    "law": "L. 132-4-1 du CU",
    "name": "Demande de la note d'enjeux",
    "name_sudocuh": null,
    "order": 19,
    "phases": "Diagnostic ou PADD",
    "scope_liste": [
      "ppi"
    ],
    "scope_sugg": [
      "ppi"
    ],
    "structurant": false
  },
  {
    "code": "NOTENJ",
    "condition": null,
    "impact": null,
    "law": null,
    "name": "Transmission de la note d'enjeux",
    "name_sudocuh": null,
    "order": 20,
    "phases": null,
    "scope_liste": [
      "ppi"
    ],
    "scope_sugg": [],
    "structurant": true
  },
  {
    "code": "READNOTE",
    "condition": "Quand elle a été faite (obligatoire si l'EPCI l'a demandé, facultative dans tous les autres cas)",
    "impact": null,
    "law": null,
    "name": "Prise en compte de la note d'enjeux dans le projet",
    "name_sudocuh": null,
    "order": 21,
    "phases": null,
    "scope_liste": [
      "pp",
      "ppi",
      "rms"
    ],
    "scope_sugg": [
      "pp",
      "ppi",
      "rms"
    ],
    "structurant": false
  },
  {
    "code": "PACCOMP",
    "condition": "Lorsqu'il y en a un",
    "impact": null,
    "law": null,
    "name": "Transmission du porter à connaissance complémentaire",
    "name_sudocuh": "Transmission du porter à connaissance complémentaire",
    "order": 22,
    "phases": "Toutes phases",
    "scope_liste": [
      "pp",
      "ppi"
    ],
    "scope_sugg": [],
    "structurant": false
  },
  {
    "code": "DIAGPPA",
    "condition": null,
    "impact": null,
    "law": null,
    "name": "Présentation du diagnostic aux PPA",
    "name_sudocuh": null,
    "order": 23,
    "phases": "Diagnostic",
    "scope_liste": [
      "pp",
      "ppi"
    ],
    "scope_sugg": [
      "pp",
      "ppi"
    ],
    "structurant": true
  },
  {
    "code": "STARTEVALENV",
    "condition": "Tout au long du projet\nPour PP et PPI : obligatoire\nPour RMS : obligatoire sauf SI inférieur à 5ha ET n'affecte pas N2000. Obligatoire si soumission par cas par cas ad'hoc\nPour M : obligatoire SI le projet a les mêms effets qu'une révion OU affecte un site Natura 2000 OU qu'il a été soumis à évaluation environnementale à l'issue du cas par cas ad'hoc",
    "impact": null,
    "law": "Elaboration : L. 104-1 (3°bis) et R. 104-11 (I-1°) du CU\nRévision : L. 104-1 (3°bis) et R. 104-11 (I-2°) du CU",
    "name": "Lancement de l'évaluation environnementale du projet",
    "name_sudocuh": null,
    "order": 24,
    "phases": "EE",
    "scope_liste": [
      "pp",
      "ppi",
      "rms",
      "m",
      "ms",
      "mc",
      "mlh"
    ],
    "scope_sugg": [
      "pp",
      "ppi"
    ],
    "structurant": false
  },
  {
    "code": "BUILDPADD",
    "condition": null,
    "impact": null,
    "law": null,
    "name": "Phase de construction du projet de territoire (PADD)",
    "name_sudocuh": null,
    "order": 25,
    "phases": "PADD",
    "scope_liste": [
      "pp",
      "ppi"
    ],
    "scope_sugg": [
      "pp",
      "ppi"
    ],
    "structurant": false
  },
  {
    "code": "SHOWPADD",
    "condition": null,
    "impact": null,
    "law": null,
    "name": "Présentation du PADD aux PPA",
    "name_sudocuh": null,
    "order": 26,
    "phases": "PADD",
    "scope_liste": [
      "pp",
      "ppi"
    ],
    "scope_sugg": [
      "pp",
      "ppi"
    ],
    "structurant": false
  },
  {
    "code": "PATCHPADD",
    "condition": null,
    "impact": null,
    "law": null,
    "name": "Intégration des retours sur le PADD",
    "name_sudocuh": null,
    "order": 27,
    "phases": "PADD",
    "scope_liste": [
      "pp",
      "ppi"
    ],
    "scope_sugg": [
      "pp",
      "ppi"
    ],
    "structurant": false
  },
  {
    "code": "DEBPADD",
    "condition": null,
    "impact": null,
    "law": "L. 153-12 du CU",
    "name": "Débat sur le PADD en conseil municipal ou communautaire",
    "name_sudocuh": "Débat sur le PADD ou PAS",
    "order": 28,
    "phases": "PADD",
    "scope_liste": [
      "pp"
    ],
    "scope_sugg": [
      "pp"
    ],
    "structurant": true
  },
  {
    "code": "DEBATEPADD",
    "condition": null,
    "impact": null,
    "law": "L. 153-12 du CU",
    "name": "Débat sur le PADD en conseil communautaire et en conseils communaux",
    "name_sudocuh": null,
    "order": 29,
    "phases": "PADD",
    "scope_liste": [
      "ppi"
    ],
    "scope_sugg": [
      "ppi"
    ],
    "structurant": true
  },
  {
    "code": null,
    "condition": null,
    "impact": null,
    "law": null,
    "name": "Débat sur le PADD en conseil métropolitain",
    "name_sudocuh": null,
    "order": 30,
    "phases": null,
    "scope_liste": [
      "ppi"
    ],
    "scope_sugg": [],
    "structurant": true
  },
  {
    "code": "BUILDRP",
    "condition": null,
    "impact": null,
    "law": null,
    "name": "Phase de construction du rapport de présentation",
    "name_sudocuh": null,
    "order": 31,
    "phases": "Rapport de présentation",
    "scope_liste": [
      "pp",
      "ppi"
    ],
    "scope_sugg": [
      "pp",
      "ppi"
    ],
    "structurant": false
  },
  {
    "code": "BUILDREGLEG",
    "condition": null,
    "impact": null,
    "law": null,
    "name": "Phase de construction du règlement écrit et graphique",
    "name_sudocuh": null,
    "order": 32,
    "phases": "Règlement",
    "scope_liste": [
      "pp",
      "ppi"
    ],
    "scope_sugg": [
      "pp",
      "ppi"
    ],
    "structurant": false
  },
  {
    "code": "BUILDOAP",
    "condition": null,
    "impact": null,
    "law": null,
    "name": "Phase de construction des OAP",
    "name_sudocuh": null,
    "order": 33,
    "phases": "OAP",
    "scope_liste": [
      "pp",
      "ppi"
    ],
    "scope_sugg": [
      "pp",
      "ppi"
    ],
    "structurant": false
  },
  {
    "code": "BUILDPOA",
    "condition": null,
    "impact": null,
    "law": "L. 151-45",
    "name": "Phase de construction du POA",
    "name_sudocuh": null,
    "order": 34,
    "phases": "POA",
    "scope_liste": [
      "ppi"
    ],
    "scope_sugg": [
      "ppi"
    ],
    "structurant": false
  },
  {
    "code": "SHOWPPA",
    "condition": null,
    "impact": null,
    "law": null,
    "name": "Présentation du projet complet de PLU finalisé aux PPA avant l'arrêt",
    "name_sudocuh": null,
    "order": 35,
    "phases": "Pré-arrêt",
    "scope_liste": [
      "pp",
      "ppi",
      "rms"
    ],
    "scope_sugg": [
      "pp",
      "ppi",
      "rms"
    ],
    "structurant": false
  },
  {
    "code": "PATCHLAST",
    "condition": null,
    "impact": null,
    "law": null,
    "name": "Intégration des derniers retours sur le PLU",
    "name_sudocuh": null,
    "order": 36,
    "phases": null,
    "scope_liste": [
      "pp",
      "ppi",
      "rms"
    ],
    "scope_sugg": [
      "pp",
      "ppi",
      "rms"
    ],
    "structurant": false
  },
  {
    "code": "DEROG",
    "condition": "Obligatoire SI la collectivité n'est pas couverte par un SCoT approuvé ET qu'elle veut déroger à l'article L142-4 (principe d'urbanisation limitée)",
    "impact": null,
    "law": "L. 142-5 et R. 142-2 du CU (délai de 2 mois)",
    "name": "Dérogation au principe d'urbanisation limitée -> consultation CDPENAF\n(délai 2 mois) et saisine Préfet pour avis (4 mois)",
    "name_sudocuh": "Dérogation au titre du L142-4 (ex L122-2)",
    "order": 37,
    "phases": "Arrêt du projet",
    "scope_liste": [
      "pp",
      "ppi",
      "rms",
      "m",
      "ms",
      "mlh"
    ],
    "scope_sugg": [],
    "structurant": false
  },
  {
    "code": "DEROGULPREF",
    "condition": null,
    "impact": null,
    "law": null,
    "name": "Dérogation au principe d'urbanisation limitée -> avis du préfet",
    "name_sudocuh": null,
    "order": 38,
    "phases": null,
    "scope_liste": [
      "pp",
      "ppi",
      "rms",
      "m",
      "ms",
      "mlh"
    ],
    "scope_sugg": [],
    "structurant": false
  },
  {
    "code": "CONSENVCPC",
    "condition": "Pour RMS : Obligatoire SI le projet n'affecte pas un site N2000 ET que la modification est minuere (révision inférieure à 5 ha)\nPour M et MS : Obligatoire SI la modification n'a pas pour seul objet de réduire la surface d'une zone urbaniser/à urbaniser OU n'a pas pour seul objet de réctifier une erreur matérielle OU n'est pas directement soumis à évaluation environnementale (projet ayant les mêmes effets qu'une révison OU affectant un site N2000)",
    "impact": null,
    "law": null,
    "name": "Consultation de l'autorité environnementale au cas par cas ad'hoc",
    "name_sudocuh": null,
    "order": 39,
    "phases": null,
    "scope_liste": [
      "rms",
      "m",
      "ms",
      "mc",
      "mlh"
    ],
    "scope_sugg": [
      "rms",
      "m",
      "ms",
      "mc"
    ],
    "structurant": false
  },
  {
    "code": "EXEMEVALENV",
    "condition": "Le cas échéant",
    "impact": null,
    "law": null,
    "name": "Exemption d'évaluation environnementale",
    "name_sudocuh": null,
    "order": 40,
    "phases": null,
    "scope_liste": [
      "rms",
      "m",
      "ms",
      "mc",
      "mlh"
    ],
    "scope_sugg": [],
    "structurant": false
  },
  {
    "code": null,
    "condition": "Le cas échéant, dans ce cas bascule dans \"lancement de l'évaluation environnementale\"",
    "impact": null,
    "law": "R104-33 CU",
    "name": "Soumission à évaluation environnementale -> délibération de la décision",
    "name_sudocuh": null,
    "order": 42,
    "phases": null,
    "scope_liste": [
      "rms",
      "m",
      "ms",
      "mc",
      "mlh"
    ],
    "scope_sugg": [],
    "structurant": true
  },
  {
    "code": "SUBEVALENV",
    "condition": "Le cas échéant, dans ce cas bascule dans \"lancement de l'évaluation environnementale\"",
    "impact": null,
    "law": null,
    "name": "Soumission à évaluation environnementale",
    "name_sudocuh": null,
    "order": 43,
    "phases": null,
    "scope_liste": [
      "rms",
      "m",
      "ms",
      "mc",
      "mlh"
    ],
    "scope_sugg": [],
    "structurant": true
  },
  {
    "code": "DELBILAN",
    "condition": "S'il y a eu concertation",
    "impact": null,
    "law": "R. 153-3",
    "name": "Délibération de bilan de la concertation",
    "name_sudocuh": "Délibération de bilan de la concertation",
    "order": 44,
    "phases": "Concertation",
    "scope_liste": [
      "pp",
      "ppi",
      "rms",
      "m",
      "ms",
      "mc",
      "mlh"
    ],
    "scope_sugg": [
      "pp",
      "ppi",
      "rms"
    ],
    "structurant": false
  },
  {
    "code": "NOTPPA",
    "condition": null,
    "impact": null,
    "law": null,
    "name": "Notification du dossier aux PPA et communes concernées",
    "name_sudocuh": null,
    "order": 45,
    "phases": null,
    "scope_liste": [
      "m",
      "ms",
      "mlh"
    ],
    "scope_sugg": [
      "m",
      "ms",
      "mlh"
    ],
    "structurant": false
  },
  {
    "code": null,
    "condition": null,
    "impact": null,
    "law": null,
    "name": "Avis suite à notification des PPA",
    "name_sudocuh": null,
    "order": 46,
    "phases": null,
    "scope_liste": [
      "m",
      "ms",
      "mlh"
    ],
    "scope_sugg": [
      "m",
      "ms",
      "mlh"
    ],
    "structurant": false
  },
  {
    "code": "ARRPROJ",
    "condition": null,
    "impact": null,
    "law": "L. 153-14",
    "name": "Arrêt de projet",
    "name_sudocuh": "Arrêt de projet",
    "order": 47,
    "phases": "Arrêt du projet",
    "scope_liste": [
      "pp",
      "ppi",
      "rms",
      "mc"
    ],
    "scope_sugg": [
      "pp",
      "ppi",
      "rms"
    ],
    "structurant": true
  },
  {
    "code": "SHOWOAP",
    "condition": null,
    "impact": null,
    "law": "L.153-15",
    "name": "Présentation des OAP et règlement aux communes du territoire",
    "name_sudocuh": null,
    "order": 48,
    "phases": "Arrêt du projet",
    "scope_liste": [
      "ppi"
    ],
    "scope_sugg": [
      "ppi"
    ],
    "structurant": false
  },
  {
    "code": "DELIBCONSARR",
    "condition": null,
    "impact": null,
    "law": null,
    "name": "Délibération du conseil communautaire qui arrête le projet de PLU",
    "name_sudocuh": null,
    "order": 49,
    "phases": null,
    "scope_liste": [
      "ppi"
    ],
    "scope_sugg": [
      "ppi"
    ],
    "structurant": true
  },
  {
    "code": "CONSENV",
    "condition": "Pour PP et PPI : obligatoire\nPour les autres : obligatoire SI il y a eu EE",
    "impact": null,
    "law": "art. R. 104-23",
    "name": "Saisine de l'Autorité environnementale pour avis",
    "name_sudocuh": "Consultation de l'autorité environnementale",
    "order": 50,
    "phases": "Arrêt du projet",
    "scope_liste": [
      "pp",
      "ppi",
      "rms",
      "m",
      "ms",
      "mc",
      "mlh"
    ],
    "scope_sugg": [
      "pp",
      "ppi"
    ],
    "structurant": false
  },
  {
    "code": "CONSCDNPS",
    "condition": "Obligatoire SI la collectivité est en loi littorale ET le DU classe des parcs et ensembles boisés existants les plus significatifs de la commune ou du groupement de communes en espace boisé classé (EBC)\nObligatoire SI la collectivité est en loi montagne ET \n- produit une étude pour déroger au principe de continuité avec l’urbanisation existante\n- OU délimite des zones d'urbanisation future de taille et de capacité d'accueil limitées\n- OU prévoit des constructions ou aménagements à moins de 300m des rives d'un plan d'eau inférieur à 1000 ha\nObligatoire SI le document prévoit a réalisation d'une ou plusieurs unités touristiques nouvelles locales",
    "impact": null,
    "law": "L121-27 (loi littorale)\nL 122-7 et L.122-14 (loi montagne)\nL. 153-16",
    "name": "Saisine de la CDNPS pour avis",
    "name_sudocuh": "Consultation de la CDNPS",
    "order": 51,
    "phases": "Arrêt du projet",
    "scope_liste": [
      "pp",
      "ppi",
      "rms",
      "mc"
    ],
    "scope_sugg": [],
    "structurant": false
  },
  {
    "code": "CONSCDPENAF",
    "condition": "Obligatoire SI la collectivité n'est pas couverte par un SCoT approuvé ET a pour conséquence une réduction des surfaces des espaces naturels, agricoles et forestiers ; \nObligatoire SI le réglement du docuement prévoit en zone A et N :\n- la délimitation de secteurs de taille et de capacité d’accueil limitées (STECAL),\n- OU le changement de destination de bâtiments en dehors des STECAL,\n- OU constructions et installations nécessaires à la transformation, au conditionnement et à la commercialisation des produits agricoles,\n- OU les extensions de bâtiments d’habitation existants et l’ajout d’annexe(s) à ces bâtiments ;",
    "impact": null,
    "law": "L. 153-16\nL151-11 à 13",
    "name": "Saisine de la CDPENAF pour avis",
    "name_sudocuh": "Consultation de la CDPENAF",
    "order": 52,
    "phases": "Arrêt du projet",
    "scope_liste": [
      "pp",
      "ppi",
      "rms",
      "m",
      "ms",
      "mc",
      "mlh"
    ],
    "scope_sugg": [
      "pp",
      "ppi",
      "rms"
    ],
    "structurant": false
  },
  {
    "code": "CONSPPA",
    "condition": null,
    "impact": null,
    "law": "L. 153-16\nL132-7",
    "name": "Consultation des PPA",
    "name_sudocuh": "Consultation des PPA",
    "order": 53,
    "phases": "Arrêt du projet",
    "scope_liste": [
      "pp",
      "ppi"
    ],
    "scope_sugg": [
      "pp",
      "ppi"
    ],
    "structurant": false
  },
  {
    "code": "CONSULTCOMREG",
    "condition": "Obligatoire SI le PLUi tient lieu de PLH",
    "impact": null,
    "law": "L. 153-16",
    "name": "Consultation du comité régional de l'habitat et de l'hébergement",
    "name_sudocuh": "Consultation du comité régional de l'habitat et de l'hébergement",
    "order": 54,
    "phases": "Arrêt du projet",
    "scope_liste": [
      "ppi"
    ],
    "scope_sugg": [
      "ppi"
    ],
    "structurant": false
  },
  {
    "code": "CONSULTINQZ",
    "condition": "Obligatoire SI le PLU réduit des espaces agricoles et forestiers",
    "impact": null,
    "law": "R153-6",
    "name": "Consultation de l'Institut national de l'origine et de la qualité dans les zones d'appellation d'origine contrôlée et, le cas échéant, du Centre national de la propriété forestière",
    "name_sudocuh": null,
    "order": 55,
    "phases": "Arrêt du projet",
    "scope_liste": [
      "pp",
      "ppi"
    ],
    "scope_sugg": [],
    "structurant": false
  },
  {
    "code": "AVISZAC",
    "condition": "Obligatoire SI le projet a pour objet ou pour effet de modifier les règles d'urbanisme applicables à l'intérieur d'un périmètre de zone d'aménagement concerté créée à l'initiative d'une personne publique ou d'un EPCI autre que l'établissement public de coopération intercommunale ou la commune qui porte la modification",
    "impact": null,
    "law": null,
    "name": "Avis de la personne publique ou de l'EPCI en cas de modification d'une ZAC",
    "name_sudocuh": null,
    "order": 56,
    "phases": null,
    "scope_liste": [
      "m"
    ],
    "scope_sugg": [],
    "structurant": false
  },
  {
    "code": "AVISENV",
    "condition": null,
    "impact": null,
    "law": null,
    "name": "Réception de l'avis de l'autorité environnementale",
    "name_sudocuh": "Avis de l'autorité environnementale",
    "order": 57,
    "phases": "Arrêt du projet",
    "scope_liste": [
      "pp",
      "ppi",
      "rms",
      "m",
      "ms",
      "mc",
      "mlh"
    ],
    "scope_sugg": [
      "pp",
      "ppi"
    ],
    "structurant": false
  },
  {
    "code": "AVICDPENAF",
    "condition": null,
    "impact": null,
    "law": null,
    "name": "Réception de l'avis de la CDPENAF",
    "name_sudocuh": "Avis de la CDPENAF",
    "order": 58,
    "phases": "?",
    "scope_liste": [
      "pp",
      "ppi",
      "rms",
      "m",
      "ms",
      "mc",
      "mlh"
    ],
    "scope_sugg": [
      "pp",
      "ppi",
      "rms"
    ],
    "structurant": false
  },
  {
    "code": "AVICDNPS",
    "condition": null,
    "impact": null,
    "law": null,
    "name": "Réception de l'avis de la CDNPS",
    "name_sudocuh": "Avis de la CDNPS",
    "order": 59,
    "phases": "?",
    "scope_liste": [
      "pp",
      "ppi",
      "rms",
      "mc"
    ],
    "scope_sugg": [
      "pp",
      "ppi",
      "rms"
    ],
    "structurant": false
  },
  {
    "code": "AVISETAT",
    "condition": null,
    "impact": null,
    "law": null,
    "name": "Transmission de l'avis de l'État - favorable avec réserves",
    "name_sudocuh": null,
    "order": 61,
    "phases": null,
    "scope_liste": [
      "pp",
      "ppi",
      "m",
      "mlh"
    ],
    "scope_sugg": [],
    "structurant": true
  },
  {
    "code": "AVISETAT",
    "condition": null,
    "impact": null,
    "law": null,
    "name": "Transmission de l'avis de l'État - favorable",
    "name_sudocuh": null,
    "order": 62,
    "phases": null,
    "scope_liste": [
      "pp",
      "ppi",
      "m",
      "mlh"
    ],
    "scope_sugg": [],
    "structurant": true
  },
  {
    "code": "AVISETAT",
    "condition": null,
    "impact": null,
    "law": null,
    "name": "Transmission de l'avis de l'État - défavorbale",
    "name_sudocuh": null,
    "order": 63,
    "phases": null,
    "scope_liste": [
      "pp",
      "ppi",
      "m",
      "mlh"
    ],
    "scope_sugg": [],
    "structurant": true
  },
  {
    "code": null,
    "condition": null,
    "impact": null,
    "law": null,
    "name": "Transmission de l'avis PPA - Région",
    "name_sudocuh": null,
    "order": 64,
    "phases": null,
    "scope_liste": [
      "pp",
      "ppi"
    ],
    "scope_sugg": [],
    "structurant": false
  },
  {
    "code": "AVISENAF",
    "condition": "Obligatoire SI la commune ou EPCI le demande ET si il y a lieu vis-à-vis du projet",
    "impact": null,
    "law": null,
    "name": "Avis de l'Etat sur l'analyse de la consomation d'ENAF et la modération de cette consommation",
    "name_sudocuh": null,
    "order": 65,
    "phases": null,
    "scope_liste": [
      "m"
    ],
    "scope_sugg": [],
    "structurant": false
  },
  {
    "code": "EXAMPPA",
    "condition": null,
    "impact": null,
    "law": "L. 153-34 et R. 153-12",
    "name": "Examen conjoint des PPA",
    "name_sudocuh": null,
    "order": 66,
    "phases": null,
    "scope_liste": [
      "rms",
      "mc"
    ],
    "scope_sugg": [
      "rms",
      "mc"
    ],
    "structurant": true
  },
  {
    "code": null,
    "condition": null,
    "impact": null,
    "law": null,
    "name": "Décision de recourir à la mise à disposition",
    "name_sudocuh": null,
    "order": 67,
    "phases": null,
    "scope_liste": [
      "mlh"
    ],
    "scope_sugg": [],
    "structurant": false
  },
  {
    "code": null,
    "condition": null,
    "impact": null,
    "law": null,
    "name": "Délibération sur les modalités de mise à disposition",
    "name_sudocuh": null,
    "order": 68,
    "phases": null,
    "scope_liste": [
      "ms",
      "mlh"
    ],
    "scope_sugg": [],
    "structurant": false
  },
  {
    "code": null,
    "condition": "8 jours au moins avant le début",
    "impact": null,
    "law": null,
    "name": "Publicité sur mise à disposition du public",
    "name_sudocuh": null,
    "order": 69,
    "phases": null,
    "scope_liste": [
      "ms",
      "mlh"
    ],
    "scope_sugg": [
      "ms"
    ],
    "structurant": false
  },
  {
    "code": "DEBINFO",
    "condition": "1 mois",
    "impact": null,
    "law": "L. 153-47 CU",
    "name": "Début de mise à disposition du public",
    "name_sudocuh": null,
    "order": 70,
    "phases": null,
    "scope_liste": [
      "ms",
      "mlh"
    ],
    "scope_sugg": [
      "ms"
    ],
    "structurant": true
  },
  {
    "code": "FININFO",
    "condition": null,
    "impact": null,
    "law": "L. 153-47 CU",
    "name": "Fin de mise à disposition du public",
    "name_sudocuh": null,
    "order": 71,
    "phases": null,
    "scope_liste": [
      "ms",
      "mlh"
    ],
    "scope_sugg": [
      "ms"
    ],
    "structurant": true
  },
  {
    "code": null,
    "condition": null,
    "impact": null,
    "law": null,
    "name": "Bilan de la mise à disposition",
    "name_sudocuh": null,
    "order": 72,
    "phases": null,
    "scope_liste": [
      "mlh"
    ],
    "scope_sugg": [],
    "structurant": false
  },
  {
    "code": null,
    "condition": null,
    "impact": null,
    "law": null,
    "name": "Décision de recourir à la participation du public par voie électronique (PPVE)",
    "name_sudocuh": null,
    "order": 73,
    "phases": null,
    "scope_liste": [
      "mlh"
    ],
    "scope_sugg": [],
    "structurant": false
  },
  {
    "code": null,
    "condition": null,
    "impact": null,
    "law": null,
    "name": "Constitution et mise à disposition du dossier de PPVE",
    "name_sudocuh": null,
    "order": 74,
    "phases": null,
    "scope_liste": [
      "mlh"
    ],
    "scope_sugg": [],
    "structurant": false
  },
  {
    "code": null,
    "condition": null,
    "impact": null,
    "law": null,
    "name": "Publicité préalable à l'ouverture de la PPVE",
    "name_sudocuh": null,
    "order": 75,
    "phases": null,
    "scope_liste": [
      "mlh"
    ],
    "scope_sugg": [],
    "structurant": false
  },
  {
    "code": null,
    "condition": null,
    "impact": null,
    "law": null,
    "name": "Début de la participation du public par voie électronique",
    "name_sudocuh": null,
    "order": 76,
    "phases": null,
    "scope_liste": [
      "mlh"
    ],
    "scope_sugg": [],
    "structurant": true
  },
  {
    "code": null,
    "condition": null,
    "impact": null,
    "law": null,
    "name": "Fin de la participation du public par voie électronique",
    "name_sudocuh": null,
    "order": 77,
    "phases": null,
    "scope_liste": [
      "mlh"
    ],
    "scope_sugg": [],
    "structurant": true
  },
  {
    "code": null,
    "condition": null,
    "impact": null,
    "law": null,
    "name": "Synthèse de la participation du public par voie électronique",
    "name_sudocuh": null,
    "order": 78,
    "phases": null,
    "scope_liste": [
      "mlh"
    ],
    "scope_sugg": [],
    "structurant": false
  },
  {
    "code": null,
    "condition": null,
    "impact": null,
    "law": null,
    "name": "Décision de recourir à l'enquête publique",
    "name_sudocuh": null,
    "order": 79,
    "phases": "Enquête publique",
    "scope_liste": [
      "mlh"
    ],
    "scope_sugg": [],
    "structurant": false
  },
  {
    "code": "ARRENQ",
    "condition": null,
    "impact": null,
    "law": "L. 153-19",
    "name": "Arrêté d'enquête publique",
    "name_sudocuh": "Arrêté d'enquête publique",
    "order": 80,
    "phases": "Enquête publique",
    "scope_liste": [
      "pp",
      "ppi",
      "rms",
      "m",
      "mc",
      "mlh"
    ],
    "scope_sugg": [
      "pp",
      "ppi",
      "rms",
      "m",
      "mc"
    ],
    "structurant": false
  },
  {
    "code": "DEBENQ",
    "condition": null,
    "impact": null,
    "law": null,
    "name": "Début d'enquête publique",
    "name_sudocuh": "Début d'enquête publique",
    "order": 81,
    "phases": "Enquête publique",
    "scope_liste": [
      "pp",
      "ppi",
      "rms",
      "m",
      "mc",
      "mlh"
    ],
    "scope_sugg": [
      "pp",
      "ppi",
      "rms",
      "m",
      "mc"
    ],
    "structurant": true
  },
  {
    "code": "FINENQ",
    "condition": null,
    "impact": null,
    "law": null,
    "name": "Fin d'enquête publique",
    "name_sudocuh": "Fin d'enquête publique",
    "order": 82,
    "phases": "Enquête publique",
    "scope_liste": [
      "pp",
      "ppi",
      "rms",
      "m",
      "mc",
      "mlh"
    ],
    "scope_sugg": [
      "pp",
      "ppi",
      "rms",
      "m",
      "mc"
    ],
    "structurant": true
  },
  {
    "code": "RAPCOMENQ",
    "condition": null,
    "impact": null,
    "law": null,
    "name": "Rapport et conclusions de l'enquête publique",
    "name_sudocuh": "Rapport du commissaire enquêteur",
    "order": 83,
    "phases": "Enquête publique",
    "scope_liste": [
      "pp",
      "ppi",
      "rms",
      "m",
      "mc",
      "mlh"
    ],
    "scope_sugg": [
      "pp",
      "ppi",
      "rms",
      "m",
      "mc"
    ],
    "structurant": false
  },
  {
    "code": "PATCHENQPUB",
    "condition": null,
    "impact": null,
    "law": null,
    "name": "Intégration des retours faits pendant l'enquête publique",
    "name_sudocuh": null,
    "order": 84,
    "phases": "Enquête publique",
    "scope_liste": [
      "pp",
      "ppi",
      "rms",
      "m",
      "mc",
      "mlh"
    ],
    "scope_sugg": [
      "pp",
      "ppi",
      "rms",
      "m",
      "mc"
    ],
    "structurant": false
  },
  {
    "code": "AVICOM",
    "condition": null,
    "impact": null,
    "law": null,
    "name": "Avis de la commune sur le dossier de MC",
    "name_sudocuh": "Avis de la commune sur le dossier de MC",
    "order": 85,
    "phases": null,
    "scope_liste": [
      "mc"
    ],
    "scope_sugg": [],
    "structurant": false
  },
  {
    "code": "CONFINTERCO",
    "condition": null,
    "impact": null,
    "law": "L 153-21 (1°)",
    "name": "Conférence intercommunale",
    "name_sudocuh": "Conférence intercommunale",
    "order": 86,
    "phases": "avant l'Approbation",
    "scope_liste": [
      "ppi"
    ],
    "scope_sugg": [
      "ppi"
    ],
    "structurant": false
  },
  {
    "code": "ABAND",
    "condition": null,
    "impact": "abandon",
    "law": null,
    "name": "Abandon",
    "name_sudocuh": "Abandon",
    "order": 87,
    "phases": "Avant l'approbation",
    "scope_liste": [
      "pp",
      "ppi",
      "rms",
      "m",
      "ms",
      "mc",
      "mj"
    ],
    "scope_sugg": [],
    "structurant": true
  },
  {
    "code": "MISDEM",
    "condition": null,
    "impact": null,
    "law": null,
    "name": "Mise en demeure servitudes",
    "name_sudocuh": "Mise en demeure servitudes",
    "order": 88,
    "phases": null,
    "scope_liste": [
      "mj"
    ],
    "scope_sugg": [],
    "structurant": false
  },
  {
    "code": "DELAPP",
    "condition": null,
    "impact": "opposable",
    "law": "L. 153-21 (2°)",
    "name": "Délibération d'approbation du conseil municipal ou communautaire",
    "name_sudocuh": "Délibération d'approbation",
    "order": 89,
    "phases": "Approbation",
    "scope_liste": [
      "pp",
      "ppi",
      "rms",
      "m",
      "ms",
      "mlh"
    ],
    "scope_sugg": [
      "pp",
      "ppi",
      "rms",
      "m",
      "ms",
      "mlh"
    ],
    "structurant": true
  },
  {
    "code": "ARRMP",
    "condition": null,
    "impact": null,
    "law": null,
    "name": "Arrêté du Maire ou du Préfet ou de l'EPCI",
    "name_sudocuh": "Arrêté du Maire ou du Préfet ou de l'EPCI",
    "order": 90,
    "phases": "Approbation",
    "scope_liste": [
      "mj"
    ],
    "scope_sugg": [],
    "structurant": true
  },
  {
    "code": "DUP",
    "condition": null,
    "impact": null,
    "law": null,
    "name": "DUP emportant mise en compatibilité",
    "name_sudocuh": "DUP emportant mise en compatibilité",
    "order": 91,
    "phases": "Approbation",
    "scope_liste": [
      "mc"
    ],
    "scope_sugg": [],
    "structurant": true
  },
  {
    "code": "DIG",
    "condition": null,
    "impact": null,
    "law": null,
    "name": "Déclaration d'intérêt général",
    "name_sudocuh": "Déclaration d'intérêt général",
    "order": 92,
    "phases": "Approbation",
    "scope_liste": [
      "mc"
    ],
    "scope_sugg": [],
    "structurant": false
  },
  {
    "code": "DELMEC",
    "condition": null,
    "impact": null,
    "law": null,
    "name": "Délibération décidant de la mise en compatibilité",
    "name_sudocuh": "Délibération décidant de la mise en compatibilité",
    "order": 93,
    "phases": "Approbation",
    "scope_liste": [
      "mc"
    ],
    "scope_sugg": [],
    "structurant": true
  },
  {
    "code": "TRANSCONT",
    "condition": null,
    "impact": null,
    "law": "L. 153-23",
    "name": "Transmission au contrôle de légalité",
    "name_sudocuh": "Transmission au contrôle de légalité",
    "order": 94,
    "phases": "Caractère exécutoire",
    "scope_liste": [
      "ppi",
      "pp",
      "rms",
      "m",
      "ms",
      "mc",
      "mj",
      "mlh"
    ],
    "scope_sugg": [
      "ppi",
      "pp",
      "rms",
      "m",
      "ms",
      "mc",
      "mj",
      "mlh"
    ],
    "structurant": true
  },
  {
    "code": "ADSPRESS",
    "condition": null,
    "impact": null,
    "law": "R. 153-21",
    "name": "Publicité dans la presse",
    "name_sudocuh": "Publicité dans la presse",
    "order": 95,
    "phases": "Caractère exécutoire",
    "scope_liste": [
      "pp",
      "ppi",
      "rms",
      "m",
      "ms",
      "mlh"
    ],
    "scope_sugg": [
      "pp",
      "ppi",
      "rms",
      "m",
      "ms",
      "mlh"
    ],
    "structurant": false
  },
  {
    "code": "AFF",
    "condition": null,
    "impact": null,
    "law": "R. 153-21",
    "name": "Affichage en commune",
    "name_sudocuh": "Affichage en commune",
    "order": 96,
    "phases": "Caractère exécutoire",
    "scope_liste": [
      "ppi",
      "pp",
      "rms",
      "m",
      "ms",
      "mc",
      "mj",
      "mlh"
    ],
    "scope_sugg": [
      "ppi",
      "pp",
      "rms",
      "m",
      "ms",
      "mc",
      "mj",
      "mlh"
    ],
    "structurant": false
  },
  {
    "code": "AFFEPCI",
    "condition": null,
    "impact": null,
    "law": "R. 153-21",
    "name": "Affichage au siège de l'EPCI et dans toutes les communes",
    "name_sudocuh": "Affichage au siège de l'EPCI et dans toutes les communes",
    "order": 97,
    "phases": "Caractère exécutoire",
    "scope_liste": [
      "ppi",
      "pp",
      "rms",
      "m",
      "ms",
      "mc",
      "mj",
      "mlh"
    ],
    "scope_sugg": [
      "ppi"
    ],
    "structurant": false
  },
  {
    "code": "PUB",
    "condition": null,
    "impact": null,
    "law": "L. 153-23",
    "name": "Publication du PLU sur le GPU",
    "name_sudocuh": "Publication du PLU sur le GPU",
    "order": 98,
    "phases": "Caractère exécutoire",
    "scope_liste": [
      "ppi",
      "pp",
      "rms",
      "m",
      "ms",
      "mc",
      "mj",
      "mlh"
    ],
    "scope_sugg": [
      "pp",
      "ppi",
      "rms",
      "m",
      "ms",
      "mc",
      "mj"
    ],
    "structurant": false
  },
  {
    "code": "EXECUT",
    "condition": null,
    "impact": "opposable",
    "law": null,
    "name": "Caractère exécutoire",
    "name_sudocuh": "Caractère exécutoire",
    "order": 99,
    "phases": null,
    "scope_liste": [
      "ppi",
      "pp",
      "rms",
      "m",
      "ms",
      "mc",
      "mj",
      "mlh"
    ],
    "scope_sugg": [
      "pp",
      "ppi"
    ],
    "structurant": true
  },
  {
    "code": "RECGRAC",
    "condition": null,
    "impact": null,
    "law": null,
    "name": "Recours gracieux de l'État",
    "name_sudocuh": "Recours gracieux de l'État",
    "order": 100,
    "phases": "?",
    "scope_liste": [
      "ppi",
      "pp",
      "rms",
      "m",
      "ms",
      "mc",
      "mj",
      "mlh"
    ],
    "scope_sugg": [],
    "structurant": false
  },
  {
    "code": "BACKPRESCR",
    "condition": null,
    "impact": "abandonné",
    "law": null,
    "name": "Retrait de la délibération de prescription",
    "name_sudocuh": null,
    "order": 101,
    "phases": null,
    "scope_liste": [
      "pp",
      "ppi",
      "rms",
      "m",
      "ms",
      "mlh"
    ],
    "scope_sugg": [],
    "structurant": true
  },
  {
    "code": "BACKAPPROB",
    "condition": null,
    "impact": "en cours",
    "law": null,
    "name": "Retrait de la délibération d'approbation",
    "name_sudocuh": null,
    "order": 102,
    "phases": null,
    "scope_liste": [
      "pp",
      "ppi",
      "rms",
      "m",
      "ms",
      "mlh"
    ],
    "scope_sugg": [],
    "structurant": true
  },
  {
    "code": "DESISGRAC",
    "condition": null,
    "impact": null,
    "law": null,
    "name": "Désistement recours gracieux de l’État",
    "name_sudocuh": null,
    "order": 103,
    "phases": null,
    "scope_liste": [
      "pp",
      "ppi",
      "rms",
      "m",
      "ms",
      "mlh"
    ],
    "scope_sugg": [],
    "structurant": false
  },
  {
    "code": "ANNULTAP",
    "condition": null,
    "impact": null,
    "law": null,
    "name": "Annulation TA partielle",
    "name_sudocuh": null,
    "order": 104,
    "phases": null,
    "scope_liste": [
      "ppi",
      "pp",
      "rms",
      "m",
      "ms",
      "mc",
      "mj",
      "mlh"
    ],
    "scope_sugg": [],
    "structurant": true
  },
  {
    "code": "ANNULTA",
    "condition": null,
    "impact": "annulé",
    "law": null,
    "name": "Annulation TA totale",
    "name_sudocuh": null,
    "order": 105,
    "phases": "?",
    "scope_liste": [
      "ppi",
      "pp",
      "rms",
      "m",
      "ms",
      "mc",
      "mj",
      "mlh"
    ],
    "scope_sugg": [],
    "structurant": true
  },
  {
    "code": "BACKANNUL",
    "condition": null,
    "impact": "opposable",
    "law": null,
    "name": "Retrait de l'annulation totale",
    "name_sudocuh": null,
    "order": 106,
    "phases": null,
    "scope_liste": [
      "ppi",
      "pp",
      "rms",
      "m",
      "ms",
      "mc",
      "mj",
      "mlh"
    ],
    "scope_sugg": [],
    "structurant": true
  },
  {
    "code": "ARRABRO",
    "condition": null,
    "impact": "abrogé",
    "law": "R153-19",
    "name": "Abrogation",
    "name_sudocuh": "Arrêté d'abrogation",
    "order": 107,
    "phases": null,
    "scope_liste": [
      "pp",
      "ppi"
    ],
    "scope_sugg": [],
    "structurant": true
  },
  {
    "code": "BIL3ANSVH",
    "condition": null,
    "impact": null,
    "law": "L. 153-28 et L. 153-29",
    "name": "Bilan à 3 ans sur le volet habitat",
    "name_sudocuh": null,
    "order": 108,
    "phases": "Bilan/évaluation",
    "scope_liste": [
      "ppi"
    ],
    "scope_sugg": [
      "ppi"
    ],
    "structurant": false
  },
  {
    "code": "RAPARTIF",
    "condition": null,
    "impact": null,
    "law": "L. 153-27 dernier alinéa du CU\n\n\nArticle L 22-31-1 (code général collectivités territoriales)",
    "name": "Rapport d'artificialisation des sols",
    "name_sudocuh": null,
    "order": 109,
    "phases": "Bilan/évaluation",
    "scope_liste": [
      "pp",
      "ppi"
    ],
    "scope_sugg": [],
    "structurant": false
  },
  {
    "code": "EVAL6ANS",
    "condition": null,
    "impact": null,
    "law": "L. 153-27 du CU",
    "name": "Evaluation du PLU au bout de 6 ans ou révision substantielle si besoin",
    "name_sudocuh": null,
    "order": 110,
    "phases": "Bilan/évaluation",
    "scope_liste": [
      "pp",
      "ppi"
    ],
    "scope_sugg": [
      "pp",
      "ppi"
    ],
    "structurant": true
  },
  {
    "code": null,
    "condition": null,
    "impact": null,
    "law": null,
    "name": "Avis suite au contrôle de légalité",
    "name_sudocuh": null,
    "order": 112,
    "phases": null,
    "scope_liste": [
      "ppi",
      "pp",
      "rms",
      "m",
      "ms",
      "mc",
      "mj",
      "mlh"
    ],
    "scope_sugg": [],
    "structurant": true
  },
  {
    "code": null,
    "condition": null,
    "impact": null,
    "law": null,
    "name": "Retrait de l'arrêt de projet",
    "name_sudocuh": null,
    "order": 113,
    "phases": null,
    "scope_liste": [
      "pp",
      "ppi",
      "rms"
    ],
    "scope_sugg": [],
    "structurant": true
  },
  {
    "code": null,
    "condition": null,
    "impact": null,
    "law": null,
    "name": "Compte-rendu de réunion PPA",
    "name_sudocuh": null,
    "order": 114,
    "phases": null,
    "scope_liste": [
      "pp",
      "ppi",
      "rms",
      "m",
      "ms",
      "mc",
      "mlh"
    ],
    "scope_sugg": [],
    "structurant": false
  },
  {
    "code": null,
    "condition": null,
    "impact": null,
    "law": null,
    "name": "Réunion de travail",
    "name_sudocuh": null,
    "order": 115,
    "phases": null,
    "scope_liste": [
      "pp",
      "ppi",
      "rms",
      "m",
      "ms",
      "mc",
      "mlh"
    ],
    "scope_sugg": [],
    "structurant": false
  }
]
